{
  "https://automaton-media.com/articles/newsjp/nyanjet-20260311-428329/": {
    "title": "空飛ぶニャンコ爆誕！激ムズ爽快アクション『nyanjet』3月13日配信決定！未知の絶景へレッツゴー！",
    "tags": "Game",
    "sentiment": "positive",
    "sentiment_text": "中毒性MAXの期待作！",
    "rating": 5,
    "time_ago": "1時間前",
    "url": "https://automaton-media.com/articles/newsjp/nyanjet-20260311-428329/",
    "summary_bullets": [
      "ジェットパックを駆使して大空を駆け巡る！キュートな猫が主役の高難度アクションゲームがついに登場！",
      "3月13日配信決定！PC（Steam）向け『nyanjet』で、まだ見ぬ景色を目指す空の旅へ出発だ！",
      "挫折必至だけど、その先の絶景と達成感は格別！中毒性MAXのプレイ体験に期待大！"
    ],
    "insight": "猫がジェットパックで空を飛ぶというユニークな設定と、“挫折必至”と銘打たれた高難度アクションの組み合わせが最大の魅力。失敗を乗り越えて到達する未知の景色は、きっと最高のカタルシスを与えてくれるだろう。",
    "action_plan": "高難度アクション好きはSteamストアページでウィッシュリストに追加し、配信日を心待ちにしましょう！『Getting Over It』のような中毒性のあるゲームが好きな人にも超おすすめ！",
    "image_keyword": "cat jetpack game",
    "technical_terms": [
      {
        "term": "ジェットパック",
        "explanation": "ジェット推進を利用して、人間や動物が空中を移動するための装置です。"
      },
      {
        "term": "高難度アクション",
        "explanation": "操作やゲームプレイが非常に難しく、プレイヤーが何度も挑戦と失敗を繰り返しながらクリアを目指すタイプのゲームです。"
      },
      {
        "term": "Steam",
        "explanation": "Valve社が運営する、PCゲームのダウンロード販売や管理を行う世界最大のデジタル配信プラットフォームです。"
      }
    ]
  },
  "https://automaton-media.com/articles/newsjp/unreal-engine-20260311-428296/": {
    "title": "速報！ゲーム開発界に激震！Unreal EngineがついにUnityを抜き去り、シェアトップに君臨！",
    "tags": "Game",
    "sentiment": "positive",
    "sentiment_text": "業界激震のビッグニュース！",
    "rating": 5,
    "time_ago": "2時間前",
    "url": "https://automaton-media.com/articles/newsjp/unreal-engine-20260311-428296/",
    "summary_bullets": [
      "ゲーム開発の根幹を支える「ゲームエンジン」の採用率で、Unreal EngineがついにUnityを抜き去りトップに！",
      "ここ1年でUnreal Engineが驚異的な追い上げを見せ、業界の勢力図を大きく塗り替える結果に！",
      "この変化は、今後のゲームのグラフィックや表現力に劇的な進化をもたらす可能性を秘めている！"
    ],
    "insight": "圧倒的なグラフィック性能と安定性で知られるUnreal Engineが、ついにゲーム開発のメインストリームを席巻！これからのゲームがどんな革新的な体験をもたらすのか、期待値はMAXだ！",
    "action_plan": "Unreal Engineで開発された最新の美麗ゲームをプレイして、その技術の進化を肌で感じてみよう！",
    "image_keyword": "Game Engine, Unreal Engine, Market Share",
    "technical_terms": [
      {
        "term": "ゲームエンジン",
        "explanation": "ゲームを開発するための土台となるソフトウェアのこと。グラフィック表示や物理計算など、複雑な処理を簡単に行えるようにする便利なツールだよ！"
      },
      {
        "term": "Unreal Engine (UE)",
        "explanation": "Epic Gamesが開発する高性能なゲームエンジン。超リアルなグラフィックと多彩な機能で、特にAAAタイトルでよく使われているよ！"
      },
      {
        "term": "Unity",
        "explanation": "Unity Technologiesが開発する汎用性の高いゲームエンジン。インディーゲームから大規模タイトルまで幅広く利用されており、初心者でも扱いやすいのが特徴だよ！"
      }
    ]
  },
  "https://natalie.mu/comic/news/663550": {
    "title": "一夜の過ちから始まる危険な恋！イケオジの正体は…!? 『煽ってきたのは君のほうでしょ？』1巻、待望の発売！",
    "tags": "Manga",
    "sentiment": "positive",
    "sentiment_text": "ドキドキが止まらない！注目の新刊コミックが登場！",
    "rating": 4,
    "time_ago": "最近",
    "url": "https://natalie.mu/comic/news/663550",
    "summary_bullets": [
      "一夜を共にしたイケオジの正体が判明し、二人の関係が急展開！",
      "「煽ってきたのは君のほうでしょ？」1巻が遂に発売、ファン待望のストーリーが楽しめる！",
      "ミステリアスな関係から始まる大人のロマンスの行方に期待が高まる！"
    ],
    "insight": "一夜限りの関係から始まる禁断の恋、そして謎多きイケオジの意外な正体…。スリリングな展開と心ときめくセリフが、読者を深く物語へと引き込みます。",
    "action_plan": "この衝撃の展開を見逃すな！『一夜をともにしたイケオジの正体は…「煽ってきたのは君のほうでしょ？」1巻』をいますぐ手に入れて、二人のラブストーリーを追いかけましょう！",
    "image_keyword": "Romantic manga cover, Office romance comic",
    "technical_terms": []
  },
  "https://natalie.mu/comic/news/663545": {
    "title": "元恋人マトリが極秘任務で再会！胸アツ展開『ジャンプ＋』読切を要チェック！",
    "tags": "Comic",
    "sentiment": "positive",
    "sentiment_text": "期待の新作！",
    "rating": 5,
    "time_ago": "最近",
    "url": "https://natalie.mu/comic/news/663545",
    "summary_bullets": [
      "元恋人同士のマトリが、よりによって極秘任務でバディを組むことに！",
      "ジャンプ＋で新作読切が公開！スリリングな展開と恋の行方が気になる！",
      "秘密組織と元恋人の関係、二転三転するストーリーに胸がザワつく！"
    ],
    "insight": "元恋人同士という禁断の関係性で、さらに命がけの極秘任務に挑むという設定が最大の魅力。スリリングなアクションと切ないロマンスが同時に楽しめる、読者を惹きつける要素満載の一作！",
    "action_plan": "ジャンプ＋で今すぐ読切をチェックして、二人の運命を見届けよう！",
    "image_keyword": "spy romance manga",
    "technical_terms": [
      {
        "term": "マトリ",
        "explanation": "麻薬取締官の通称。麻薬や覚醒剤などの薬物犯罪を取り締まる捜査官。"
      },
      {
        "term": "ジャンプ＋",
        "explanation": "集英社が運営するウェブ漫画サービス。人気漫画が無料で読め、オリジナル作品も多数掲載されている。"
      }
    ]
  },
  "https://automaton-media.com/articles/newsjp/20260311-428278/": {
    "title": "少年×魔物、ド派手バディアクション『GOBBLE』爆誕！日本一ソフトウェアの“アイデア爆弾”が9月24日に炸裂！",
    "tags": "Game",
    "sentiment": "positive",
    "sentiment_text": "期待値爆上げの完全新作が遂に！",
    "rating": 5,
    "time_ago": "11時間前",
    "url": "https://automaton-media.com/articles/newsjp/20260311-428278/",
    "summary_bullets": [
      "少年と魔物がタッグを組む、超ド派手な「バディアクション」がゲーム界に新風を巻き起こす！",
      "日本一ソフトウェアが放つ完全新作『GOBBLE』の正式発表と、待望の9月24日発売が決定！",
      "“アイデア押し”のユニークなゲーム性に、想像を掻き立てられること間違いなし！今後の情報に大注目！"
    ],
    "insight": "日本一ソフトウェアが仕掛ける新作は、少年と魔物という異色のコンビが織りなすハイスピードで爽快なバディアクション。常識を覆す“アイデアの塊”が、新たなゲーム体験を約束します！",
    "action_plan": "日本一ソフトウェアの過去作をチェックして、その斬新な発想に触れてみましょう！さらに、今後公開されるプレイ動画や詳細情報も見逃しなく、発売日に備えましょう！",
    "image_keyword": "Fantasy Action Game",
    "technical_terms": [
      {
        "term": "バディアクション",
        "explanation": "2人組のキャラクターが協力しながら敵と戦い、様々なアクションを繰り出すゲームジャンルです。"
      },
      {
        "term": "日本一ソフトウェア",
        "explanation": "ユニークで個性的な世界観やシステムを持つゲームを多数開発している日本のゲームメーカーです。"
      },
      {
        "term": "アイデア押し",
        "explanation": "既存の枠に囚われない、斬新で独創的なゲーム性や発想を強く打ち出していることを指します。"
      }
    ]
  },
  "https://automaton-media.com/articles/newsjp/20260311-428270/": {
    "title": "あの傑作『嘘つき姫と盲目王子』がPC版で電撃登場＆即日配信開始！絵本の世界をSteamで旅しよう！",
    "tags": "Game",
    "sentiment": "positive",
    "sentiment_text": "伝説の傑作がPCで蘇る！待望のPC版、いきなり登場！",
    "rating": 5,
    "time_ago": "11時間前",
    "url": "https://automaton-media.com/articles/newsjp/20260311-428270/",
    "summary_bullets": [
      "優しく切ない傑作ゲーム『嘘つき姫と盲目王子』のPC版が電撃発表＆即日配信スタート！",
      "「絵本」シリーズの原点となる感動の物語をSteamと“日本一PCゲームズ”で体験できる！",
      "PCで蘇る美麗な世界観とストーリーに、新たなファンも旧来のファンも大興奮間違いなし！"
    ],
    "insight": "まるで絵本の中に迷い込んだような美しいグラフィックと、嘘つきの魔女と盲目の王子の間に紡がれる切なくも温かい物語の深さがこの作品の最大の魅力。PCの大画面で、その独特の世界観と感動的な体験にどっぷり浸れるのが最大の魅力です。",
    "action_plan": "まだプレイしたことがない人はもちろん、SwitchやPS4版をプレイ済みの人も、ぜひPC版の美麗グラフィックで物語を再体験してみましょう！「絵本」シリーズの他作品も要チェック！",
    "image_keyword": "storybook fantasy game",
    "technical_terms": [
      {
        "term": "Steam",
        "explanation": "PCゲームをダウンロード・購入・管理できる世界最大のプラットフォームです。"
      },
      {
        "term": "日本一PCゲームズ",
        "explanation": "ゲームメーカー「日本一ソフトウェア」が運営する、独自のPCゲーム販売プラットフォームです。"
      }
    ]
  },
  "https://automaton-media.com/articles/newsjp/20260313-428782/": {
    "title": "ヤバすぎ新作ホラー爆誕！『クロックタワー』魂を受け継ぐ極限逃走劇に震えろ！",
    "tags": "Game",
    "sentiment": "positive",
    "sentiment_text": "期待の新作キター！",
    "rating": 5,
    "time_ago": "たった今",
    "url": "https://automaton-media.com/articles/newsjp/20260313-428782/",
    "summary_bullets": [
      "伝説のホラー『クロックタワー』に敬意を表した新作『Remothered: Red Nun’s Legacy』がついに発表！",
      "ホラーゲーム特化スタジオが放つ、謎の殺人鬼に追い回される心臓バクバクの極限逃走劇が幕を開ける！",
      "不気味なシスターが追い詰める恐怖の舞台で、新たなホラー伝説の幕開けに期待が高まる！"
    ],
    "insight": "伝説のホラー『クロックタワー』の精神を受け継ぎ、謎の殺人鬼から逃げ惑う究極のサバイバルホラーが誕生！ホラーゲーム特化スタジオが贈る、息詰まる心理戦と恐怖体験に全身が震えること間違いなし！",
    "action_plan": "まずはホラーの金字塔『クロックタワー』シリーズをプレイして、その恐怖の原点に触れてみましょう！",
    "image_keyword": "survival horror game, Remothered, scary nun",
    "technical_terms": [
      {
        "term": "クロックタワー",
        "explanation": "プレイヤーが殺人鬼から逃げ回る「鬼ごっこ」形式の元祖とも言える名作ホラーゲームシリーズ！"
      },
      {
        "term": "リスペクト",
        "explanation": "ゲームや作品が、過去の別の作品に敬意を払い、影響を受けていることを示す言葉だよ！"
      },
      {
        "term": "Remothered",
        "explanation": "本作のタイトル。イタリアのホラーゲームシリーズで、過去作もスリリングな恐怖体験で人気を博しているぞ！"
      }
    ]
  },
  "https://automaton-media.com/articles/newsjp/20260312-428727/": {
    "title": "衝撃の事実発覚？！『アークナイツ：エンドフィールド』公式管理人はまさかの”ペンギン”だった？！隠された遊び心にファン騒然！",
    "tags": "Game",
    "sentiment": "positive",
    "sentiment_text": "「公式の遊び心に胸熱！」「最高の小ネタ！」「思わずニヤリの注目話題」",
    "rating": 4,
    "time_ago": "9時間前",
    "url": "https://automaton-media.com/articles/newsjp/20260312-428727/",
    "summary_bullets": [
      "『アークナイツ：エンドフィールド』の管理人アカウントが、どうやら自分を「ペンギン」だと自覚しているユニークな疑惑が浮上！",
      "アイコンのさりげない変化や発言の端々に隠された「ペンギン自覚アピール」が、ファンによって次々と発見されている状況！",
      "公式運営チームの遊び心と作品への深い愛が感じられる小ネタに、ゲーム本編への期待感がさらに高まること間違いなし！"
    ],
    "insight": "人気ゲーム『アークナイツ：エンドフィールド』の公式アカウントから垣間見える、運営チームの予想外なユーモアと創造性が最大の魅力！ゲーム外のこういったファンサービスが、作品への愛情とコミュニティの一体感を深める素晴らしい見どころとなっています。",
    "action_plan": "今すぐ『アークナイツ：エンドフィールド』の公式SNSアカウントをチェックして、隠された「ペンギン」の痕跡を一緒に探し出してみましょう！さらにゲームの最新情報も要チェックです！",
    "image_keyword": "Arknights Endfield, penguin mystery, game fun",
    "technical_terms": []
  },
  "https://automaton-media.com/articles/newsjp/20260312-428712/": {
    "title": "P-Pさんプロデュース！ 新感覚リズムゲーム『STEP THEATER』爆誕！ ステージごとにルール激変!? ノリノリで予測不能な物語に飛び込もう！",
    "tags": "Game",
    "sentiment": "positive",
    "sentiment_text": "P-Pさんファン歓喜！ 期待の新作リズムゲームが爆誕！",
    "rating": 5,
    "time_ago": "10時間前",
    "url": "https://automaton-media.com/articles/newsjp/20260312-428712/",
    "summary_bullets": [
      "人気ゲーム実況者P-Pさんが手がける、ステージごとにルールが変わる新感覚リズムゲーム『STEP THEATER』が発表！",
      "P-Pさんのユニークな世界観とゲームデザインが融合し、ファン待望の新作として大きな注目を集めています。",
      "リズムにノリノリで進む物語と予測不能なゲーム展開で、これまでにない体験が約束されるでしょう！"
    ],
    "insight": "人気実況者P-Pさんの独創的な視点と、ステージごとにルールが変化する予測不能なリズムアクションが融合！これまでにないゲーム体験が待っています！",
    "action_plan": "まずはP-Pさんの過去のゲーム実況動画をチェックして、彼のセンスを体感してみましょう！『STEP THEATER』の続報も要チェックです！",
    "image_keyword": "rhythm game, P-P streamer, unique stages",
    "technical_terms": [
      {
        "term": "ゲーム実況者",
        "explanation": "ゲームをプレイしながら解説したり、視聴者とコミュニケーションをとったりする動画配信者のこと。"
      },
      {
        "term": "リズムゲーム",
        "explanation": "音楽に合わせて画面に表示される指示にタイミングよく反応して操作するゲームジャンル。"
      }
    ]
  },
  "https://natalie.mu/comic/news/663736": {
    "title": "大注目！「スモークブルーの雨のち晴れ」が待望のドラマ化決定！武田航平＆渋谷謙人のダブル主演で春が待ち遠しい！",
    "tags": "Drama",
    "sentiment": "positive",
    "sentiment_text": "胸キュン確定！注目のドラマ化が決定！",
    "rating": 4,
    "time_ago": "最近",
    "url": "https://natalie.mu/comic/news/663736",
    "summary_bullets": [
      "大人気コミック「スモークブルーの雨のち晴れ」が、ついに2024年4月からドラマ化されることが決定！",
      "実力派俳優の武田航平と渋谷謙人がダブル主演を務め、ファンの期待が高まるキャスティングに！",
      "原作の繊細な世界観がどのように実写で表現されるのか、今から放送が待ち遠しい！"
    ],
    "insight": "このニュースの最大の魅力は、多くの読者を魅了したコミックの温かくも切ない世界観が、人気と実力を兼ね備えたダブル主演によってどのように映像化されるか。二人の俳優が織りなす繊細な感情表現とケミストリーが、物語に新たな息吹を吹き込むこと間違いなしです。",
    "action_plan": "ドラマ放送開始の4月までに、ぜひ原作コミック「スモークブルーの雨のち晴れ」を読んで、登場人物たちの魅力的な関係性を深く味わってみましょう！",
    "image_keyword": "Japanese drama adaptation",
    "technical_terms": [
      {
        "term": "ダブル主演",
        "explanation": "二人の俳優が共同で主役を務める形式。物語の中心人物が二人おり、それぞれが重要な役割を担います。"
      },
      {
        "term": "ドラマ化",
        "explanation": "漫画や小説などの原作を、テレビやWeb配信サービスで放送される連続ドラマとして映像作品にすること。"
      }
    ]
  },
  "https://natalie.mu/comic/news/663653": {
    "title": "激アツ！日本＆イタリアの共同制作アニメが爆誕！シノビーも国際デビューで世界を沸かす！",
    "tags": "Anime",
    "sentiment": "positive",
    "sentiment_text": "世界が注目！期待の新アニメ爆誕！",
    "rating": 4,
    "time_ago": "最近",
    "url": "https://natalie.mu/comic/news/663653",
    "summary_bullets": [
      "日本とイタリアがタッグを組んだ共同制作アニメが、両国で同時放送決定で話題騒然！",
      "読売テレビの公式キャラ「シノビー」がまさかの国際デビューを果たし、地球規模で愛される予感！",
      "文化の壁を越えた新しいアニメ体験に、国内外から期待の声が止まらない！",
      "日本のアニメ制作技術とイタリアのクリエイティブが融合し、これまでになかった世界観とストーリーが期待される。",
      "シノビーの登場も、親しみやすさと話題性をプラスし、幅広い層のファンを惹きつけること間違いなし！"
    ],
    "insight": "日本のアニメ文化とイタリアの豊かな創造性が融合することで、今までにない革新的な物語とビジュアルが生まれること間違いなし！読売テレビのキュートなマスコット、シノビーの国際デビューも、このプロジェクトに遊び心と親しみやすさを加え、世界中の視聴者を魅了する可能性を秘めている！",
    "action_plan": "放送開始日を速攻でチェックして、この歴史的瞬間をリアルタイムで体験しよう！公式SNSで最新情報をフォローして、制作秘話やキャラクター情報を深掘りするのも忘れずに！",
    "image_keyword": "Japan Italy Anime Collaboration",
    "technical_terms": [
      {
        "term": "共同制作アニメ",
        "explanation": "複数の国や会社が資金や技術、アイデアを出し合って一緒に作り上げるアニメ作品のこと。国際的な視点や多様な文化が融合し、より広範な audience にアピールすることが期待される。"
      },
      {
        "term": "シノビー",
        "explanation": "読売テレビの公式キャラクター。忍者の「シノ」とビーバーの「ビー」がモチーフで、可愛らしい見た目とアグレッシブなPR活動で知られる。今回は国際舞台でその魅力を発揮！"
      }
    ]
  },
  "https://natalie.mu/comic/news/663746": {
    "title": "激震走る！『キングダム』×荒木飛呂彦、井上雄彦らレジェンド漫画家夢の共演企画が爆誕！",
    "tags": "Comic",
    "sentiment": "positive",
    "sentiment_text": "夢の共演！漫画界の歴史が動く！",
    "rating": 5,
    "time_ago": "最近",
    "url": "https://natalie.mu/comic/news/663746",
    "summary_bullets": [
      "漫画界のレジェンド、荒木飛呂彦、井上雄彦、寺田克也、安彦良和らが『キングダム』を独自に描く超豪華企画が始動！",
      "普段見られない巨匠たちの『キングダム』愛と独特な解釈が垣間見える、ファン垂涎のプロジェクト。",
      "どのような作品が生まれるのか、その全貌公開に世界中の漫画ファンが固唾を飲んで待機中！"
    ],
    "insight": "漫画界の巨匠たちが、あの歴史大作『キングダム』をそれぞれの唯一無二のスタイルで描くという、まさに奇跡のコラボレーション！普段見ることのできない、巨匠たちの新たな一面と『キングダム』の知られざる可能性に触れられる絶好の機会です。",
    "action_plan": "本企画に参加する荒木飛呂彦先生、井上雄彦先生らの代表作を読み返して、先生方の作風を再確認してみましょう！そしてもちろん、壮大な『キングダム』の原作も改めてチェックして、続報に備えましょう！",
    "image_keyword": "Manga collaboration, Kingdom manga, Legendary artists",
    "technical_terms": []
  },
  "https://natalie.mu/eiga/news/663609": {
    "title": "速報！【本日公開】絶対見逃せない新作映画がスクリーンに大集合！",
    "tags": "Movie",
    "sentiment": "positive",
    "sentiment_text": "新作ラッシュに胸アツ！映画館が呼んでる！",
    "rating": 5,
    "time_ago": "最近",
    "url": "https://natalie.mu/eiga/news/663609",
    "summary_bullets": [
      "いよいよ本日！待望の新作映画たちが一斉に公開スタート！",
      "週末は映画館へ直行！大スクリーンで感動体験を味わおう。",
      "この春、あなたの心を揺さぶる傑作に出会えるチャンスを見逃すな！"
    ],
    "insight": "映画館でしか味わえない興奮と感動が、本日ついに解禁！様々なジャンルの新作がラインナップされ、きっとあなたの“推し”が見つかるはず。新たな物語の扉を開く体験が待っています。",
    "action_plan": "公式サイトや映画情報サイトで公開作品ラインナップをチェックして、気になる作品は今すぐ座席予約を済ませておきましょう！",
    "image_keyword": "new movie release, cinema, film premiere",
    "technical_terms": []
  },
  "https://natalie.mu/eiga/news/663723": {
    "title": "アラフォーBL「スモークブルーの雨のち晴れ」待望のドラマ化決定！武田航平＆渋谷謙人が織りなす大人の恋に胸キュン必至！",
    "tags": "Drama",
    "sentiment": "positive",
    "sentiment_text": "胸アツ展開！待望のドラマ化に大興奮！",
    "rating": 4,
    "time_ago": "最近",
    "url": "https://natalie.mu/eiga/news/663723",
    "summary_bullets": [
      "大人気BLコミック「スモークブルーの雨のち晴れ」が遂にドラマ化されることが決定！",
      "武田航平と渋谷謙人がアラフォー男女の繊細でリアルな恋模様を熱演、夢の共演が実現。",
      "原作ファンも納得のキャスティングで、大人の純愛ストーリーにさらなる注目が集まる！"
    ],
    "insight": "人気コミックの美しい世界観と、アラフォーならではの切なさや共感を呼ぶリアリティが、実力派俳優陣によってどのように描かれるのか見どころ満載！それぞれの想いが交錯する繊細な心理描写に期待が高まります。",
    "action_plan": "ドラマが始まる前に、ぜひ原作コミック「スモークブルーの雨のち晴れ」を読んで、作品の世界観を予習しておきましょう！",
    "image_keyword": "BL drama romance",
    "technical_terms": [
      {
        "term": "BL",
        "explanation": "ボーイズラブの略で、男性同士の恋愛を描いたフィクション作品のジャンルのこと。"
      },
      {
        "term": "アラフォー",
        "explanation": "「Around 40（アラウンド・フォーティー）」の略で、およそ40歳前後の年齢層を指す言葉。"
      }
    ]
  },
  "https://natalie.mu/eiga/news/663667": {
    "title": "女優MEGUMI、ついに映画プロデュース始動！衝撃作「FUJIKO」6月公開で映画界に旋風を巻き起こす！",
    "tags": "Movie",
    "sentiment": "positive",
    "sentiment_text": "「MEGUMI降臨！期待度MAXの新作発表！」",
    "rating": 5,
    "time_ago": "最近",
    "url": "https://natalie.mu/eiga/news/663667",
    "summary_bullets": [
      "女優MEGUMIが企画・プロデュースを手掛ける映画「FUJIKO」が2024年6月に公開決定！",
      "待望の予告映像と豪華な新キャストの情報もついに解禁され、ファンの期待が最高潮に！",
      "MEGUMIの新たな挑戦が、映画界にどんな衝撃と感動をもたらすのか、今後の展開に超注目！"
    ],
    "insight": "女優業だけでなく、美容家やクリエイターとしても活躍するMEGUMIが満を持して企画・プロデュースに挑む本作。彼女の感性と情熱が詰まった独創的な世界観は、観る者すべての心を揺さぶること間違いなしだ。",
    "action_plan": "まずはYouTubeで公開されたばかりの超刺激的な予告編をチェックして、一足早く「FUJIKO」の世界観に没入してみましょう！",
    "image_keyword": "MEGUMI movie, FUJIKO film, film production",
    "technical_terms": []
  },
  "https://natalie.mu/music/news/663765": {
    "title": "激アツコラボ爆誕！RAB龍＆THE JET BOY BANGERZがソフトバンク新CMに降臨！",
    "tags": "Music",
    "sentiment": "positive",
    "sentiment_text": "これは見逃せない！期待の超絶コラボCM爆誕！",
    "rating": 5,
    "time_ago": "最近",
    "url": "https://natalie.mu/music/news/663765",
    "summary_bullets": [
      "アニソンダンスで人気のRAB龍と、LDH発ダンス＆ボーカルグループTHE JET BOY BANGERZが異色のタッグ！",
      "二組がソフトバンクの新CMで共演し、ファン待望の豪華パフォーマンスを披露！",
      "CMを通して新たな化学反応と、さらなる活躍・認知度アップに期待高まる！"
    ],
    "insight": "アニソンダンスのパイオニアRAB龍と、LDHの最先端ダンスグループTHE JET BOY BANGERZがまさかの共演！異なるジャンルのトップランナーが交わることで生まれる、新たなダンスエンターテインメントの可能性に大注目です！",
    "action_plan": "まずはソフトバンクの新CMを即チェック！そして、RABやTHE JET BOY BANGERZのこれまでのライブ映像やMVも見て、彼らの魅力を深掘りしてみましょう！",
    "image_keyword": "Dance collaboration, Japanese idols, CM performance",
    "technical_terms": [
      {
        "term": "リアルアキバボーイズ (RAB)",
        "explanation": "アニメやゲームの楽曲でブレイクダンスを披露し、国内外で活躍する人気ダンスグループ。"
      },
      {
        "term": "THE JET BOY BANGERZ (TJBB)",
        "explanation": "LDH主催オーディションから生まれた、ダンスとボーカルを兼ね備えた注目の次世代グループ。"
      }
    ]
  },
  "https://natalie.mu/music/news/663753": {
    "title": "超特急カイ、新境地開拓！人気ドラマでまさかの「犯人役」に大抜擢！これは見逃せない！",
    "tags": "ドラマ",
    "sentiment": "positive",
    "sentiment_text": "超特急カイの新たな挑戦に胸熱！",
    "rating": 4,
    "time_ago": "最近",
    "url": "https://natalie.mu/music/news/663753",
    "summary_bullets": [
      "超特急・小笠原海が人気ドラマ「東京P.D. 警視庁広報2係」season2で、政治家を襲撃する衝撃の犯人役に挑戦！",
      "超特急のメンバーとしてだけでなく、俳優としての新たな魅力を開花させる重要な一歩となる！",
      "彼のクールなイメージとは真逆の悪役をどう演じきるのか、放送前から期待感が最高潮に高まる！"
    ],
    "insight": "超特急のカイこと小笠原海さんが、人気ドラマシリーズでまさかの悪役に挑戦！彼の持つクールなイメージと犯人役とのギャップが、ドラマに深みとスリルをもたらすこと間違いなし。新たな一面を見せる彼の演技から目が離せない！",
    "action_plan": "ドラマ『東京P.D. 警視庁広報2係』season2の放送情報を今すぐチェック！超特急の楽曲も聴きながら、カイの新たな一面に備えよう！",
    "image_keyword": "Kai Ogasawara drama actor",
    "technical_terms": []
  },
  "https://news.google.com/rss/articles/CBMif0FVX3lxTE1raTdVWXk2dmFlNC1ZaUhtc1NnYVMtaldXTXdGU2o2aG5GaG5xRXNkYWpiZ2ltcDI2Rk9SWklQVWNsem1OTlJETTg1UmlldDd3LXB0TzJPcWNCZzBjQk5QcFZqVUVrc0VMZkhjSC1DNDhCUmthRVhuSTg1aWVkbjA?oc=5": {
    "title": "スタバ愛、それとも疑問符？ あなたのカフェ選びの価値観を揺さぶる【ヤフコメ大激論】に参戦せよ！",
    "tags": "Cafe",
    "sentiment": "neutral",
    "sentiment_text": "みんなで語ろう！アツい議論が沸騰中！",
    "rating": 4,
    "time_ago": "たった今",
    "url": "https://news.google.com/rss/articles/CBMif0FVX3lxTE1raTdVWXk2dmFlNC1ZaUhtc1NnYVMtaldXTXdGU2o2aG5GaG5xRXNkYWpiZ2ltcDI2Rk9SWklQVWNsem1OTlJETTg1UmlldDd3LXB0TzJPcWNCZzBjQk5QcFZqVUVrc0VMZkhjSC1DNDhCUmthRVhuSTg1aWVkbjA?oc=5",
    "summary_bullets": [
      "「スタバの価値観」を巡ってネットで大激論が勃発！あなたはどの意見に共感する？",
      "居心地の良さ、価格設定、利用シーン…カフェ選びの基準が人それぞれであることを再認識できる、本音の応酬！",
      "この議論を機に、自分にとって最高のカフェ体験を見つけ出すヒントが隠されているかも！"
    ],
    "insight": "誰もが知る「スタバ」という普遍的な存在を通じて、現代人の多様なライフスタイルや価値観が赤裸々に語られる、まさに人間観察の縮図！自分自身のカフェ観を深く掘り下げるきっかけになること間違いなし！",
    "action_plan": "今回の議論を参考に、お気に入りのカフェで友人や家族と「最高のカフェ論争」を繰り広げてみましょう！新たな発見があるかも？",
    "image_keyword": "Cafe culture, Starbucks debate, coffee shop discussion",
    "technical_terms": []
  }
}